spectree/__init__.py
spectree/_pydantic.py
spectree/_types.py
spectree/config.py
spectree/models.py
spectree/page.py
spectree/py.typed
spectree/response.py
spectree/spec.py
spectree/utils.py
spectree/plugins/__init__.py
spectree/plugins/base.py
spectree/plugins/falcon_plugin.py
spectree/plugins/flask_plugin.py
spectree/plugins/quart_plugin.py
spectree/plugins/starlette_plugin.py
spectree/plugins/werkzeug_utils.py
spectree-2.0.1.dist-info/licenses/LICENSE
spectree-2.0.1.dist-info/METADATA
spectree-2.0.1.dist-info/WHEEL
spectree-2.0.1.dist-info/top_level.txt
spectree-2.0.1.dist-info/RECORD
