Metadata-Version: 2.4
Name: spectree
Version: 2.0.1
Summary: Generate OpenAPI document and validate request & response with Python annotations.
Author-email: Keming Yang <kemingy94@gmail.com>
License-Expression: Apache-2.0
Project-URL: Homepage, https://github.com/0b01001001/spectree
Project-URL: documentation, https://0b01001001.github.io/spectree/
Project-URL: repository, https://github.com/0b01001001/spectree
Project-URL: changelog, https://github.com/0b01001001/spectree/releases
Classifier: Intended Audience :: Developers
Classifier: Operating System :: OS Independent
Classifier: Programming Language :: Python :: 3 :: Only
Classifier: Programming Language :: Python :: 3.10
Classifier: Programming Language :: Python :: 3.11
Classifier: Programming Language :: Python :: 3.12
Classifier: Programming Language :: Python :: 3.13
Classifier: Programming Language :: Python :: 3.14
Classifier: Programming Language :: Python :: Free Threading
Classifier: Programming Language :: Python :: Implementation :: CPython
Classifier: Topic :: Software Development :: Libraries :: Python Modules
Requires-Python: >=3.10
License-File: LICENSE
Requires-Dist: pydantic<3,>=2.11
Provides-Extra: offline
Requires-Dist: offapi>=0.1.1; extra == "offline"
Provides-Extra: falcon
Requires-Dist: falcon>=3; extra == "falcon"
Provides-Extra: starlette
Requires-Dist: starlette[full]>=0.16; extra == "starlette"
Provides-Extra: flask
Requires-Dist: flask>=2; extra == "flask"
Provides-Extra: quart
Requires-Dist: quart>=0.16; extra == "quart"
Dynamic: license-file
